{
  "filePath": "app/api/github/process-one-file/route.ts",
  "title": "GitHub API Route Handler for Processing Files",
  "content": "This file defines an API route handler (`/api/github/process-one-file`) designed to process individual files from a target GitHub repository, generate documentation for them, and commit the documentation to a separate documentation repository.\n\nIt's triggered by a webhook, likely from QStash, and expects a `FileJobPayload` containing information about the file to process, the user, the repository pair, and PR details.\n\n### Purpose\n\n- To receive file processing jobs from a queue.\n- To fetch the content of a specified file from a target GitHub repository.\n- To determine if the file should be documented using `shouldSkipFile` and `generateDoc` from `@/lib/gemini`.\n- If documentation is to be generated:\n  - To create a JSON file for the document content in the documentation repository.\n  - To update a `_manifest.json` file in the documentation repository with information about the documented file.\n- To create a Pull Request in the documentation repository after the last file in a batch has been processed.\n\n### Key Functions and Logic\n\n- **`getReceiver()`**: Initializes and returns a QStash `Receiver` for signature verification.\n- **`fetchFileContent(token, repo, filePath)`**: Fetches the raw content of a file from the GitHub API.\n- **`readJsonFromRepo<T>(token, repo, filePath, branch?)`**: Reads and parses JSON content from a file in a GitHub repository.\n- **`writeJsonToRepo(token, repo, filePath, data, sha, message, branch?)`**: Writes JSON data to a file in a GitHub repository, creating or updating it.\n- **`createPR(token, docRepoFullName, branchName, prInfo)`**: Creates a Pull Request in the documentation repository.\n- **`handler(request)`**: The main API route handler.\n  - Verifies the QStash signature.\n  - Parses the `FileJobPayload` from the request body.\n  - Retrieves target and documentation repository details.\n  - Conditionally fetches file content and generates documentation.\n  - Updates the document JSON file and the `_manifest.json` file in the documentation repository.\n  - Triggers the creation of a Pull Request if it's the last file in the processing batch.\n\n### Usage Example (Conceptual)\n\nThis route is intended to be called by a background job processing system (like QStash). A typical payload might look like:\n\n```json\n{\n  \"userId\": \"user-123\",\n  \"pairId\": \"repo-pair-abc\",\n  \"filePath\": \"src/components/Button.tsx\",\n  \"branchName\": \"docs-update-abcdef1\",\n  \"isLastFile\": false,\n  \"prInfo\": {\n    \"headCommitId\": \"abcdef1234567890abcdef1234567890abcdef12\",\n    \"headCommitMessage\": \"feat: add new button component\",\n    \"pusher\": \"octocat\"\n  }\n}\n```\n\nWhen `isLastFile` is true, a PR will be created in the documentation repository. The `targetRepo` and `docRepo` are fetched based on `userId` and `pairId` using helper functions.\n\n### Dependencies\n\n- `@upstash/qstash` for webhook verification.\n- `@ /lib/gemini` for documentation generation and skipping logic.\n- `@ /lib/repo-pairs` for fetching repository details."
}
